Talnakh/StepFunctions/Patterns/__init__.py
Talnakh/StepFunctions/Patterns/py.typed
Talnakh/StepFunctions/Patterns/_jsii/__init__.py
Talnakh/StepFunctions/Patterns/_jsii/cdk-stepfunctions-patterns@0.1.5.jsii.tgz
cdk_stepfunctions_patterns-0.1.5.dist-info/METADATA
cdk_stepfunctions_patterns-0.1.5.dist-info/WHEEL
cdk_stepfunctions_patterns-0.1.5.dist-info/top_level.txt
cdk_stepfunctions_patterns-0.1.5.dist-info/RECORD
