Metadata-Version: 2.1
Name: cdk-stepfunctions-patterns
Version: 0.1.5
Summary: A set of Step Functions high-level patterns.
Home-page: https://github.com/kolomied/cdk-stepfunctions-patterns#readme
Author: Dmitry Kolomiets<kolomied@amazon.co.uk>
License: MIT
Project-URL: Source, https://github.com/kolomied/cdk-stepfunctions-patterns.git
Platform: UNKNOWN
Classifier: Intended Audience :: Developers
Classifier: Operating System :: OS Independent
Classifier: Programming Language :: JavaScript
Classifier: Programming Language :: Python :: 3 :: Only
Classifier: Programming Language :: Python :: 3.6
Classifier: Programming Language :: Python :: 3.7
Classifier: Programming Language :: Python :: 3.8
Classifier: Typing :: Typed
Classifier: Development Status :: 4 - Beta
Classifier: License :: OSI Approved
Requires-Python: >=3.6
Requires-Dist: aws-cdk.aws-lambda (==1.49.1)
Requires-Dist: aws-cdk.aws-stepfunctions-tasks (==1.49.1)
Requires-Dist: aws-cdk.aws-stepfunctions (==1.49.1)
Requires-Dist: aws-cdk.core (==1.49.1)
Requires-Dist: constructs (<4.0.0,>=3.0.4)
Requires-Dist: jsii (<2.0.0,>=1.12.0)
Requires-Dist: publication (>=0.0.3)
